caikit_tgis_backend/__init__.py
caikit_tgis_backend/_version.py
caikit_tgis_backend/generation.proto
caikit_tgis_backend/load_balancing_proxy.py
caikit_tgis_backend/managed_tgis_subprocess.py
caikit_tgis_backend/tgis_backend.py
caikit_tgis_backend/tgis_connection.py
caikit_tgis_backend/version.py
caikit_tgis_backend/protobufs/__init__.py
caikit_tgis_backend/protobufs/generation_pb2.py
caikit_tgis_backend/protobufs/generation_pb2_grpc.py
caikit_tgis_backend-0.1.38.dist-info/LICENSE
caikit_tgis_backend-0.1.38.dist-info/METADATA
caikit_tgis_backend-0.1.38.dist-info/WHEEL
caikit_tgis_backend-0.1.38.dist-info/top_level.txt
caikit_tgis_backend-0.1.38.dist-info/RECORD
