Metadata-Version: 2.1
Name: caikit-tgis-backend
Version: 0.1.38
Summary: Caikit module backend for models run in TGIS
License: Apache-2.0
Project-URL: Source, https://github.com/caikit/caikit-tgis-backend
Classifier: License :: OSI Approved :: Apache Software License
Requires-Python: ~=3.8
License-File: LICENSE
Requires-Dist: caikit <0.28.0,>=0.16.0
Requires-Dist: grpcio <2.0,>=1.35.0
Requires-Dist: requests <3,>=2.28.2
